cheaquiHelloWorld.py
cheaquiHelloWorld-0.0.3.dist-info/LICENSE
cheaquiHelloWorld-0.0.3.dist-info/METADATA
cheaquiHelloWorld-0.0.3.dist-info/WHEEL
cheaquiHelloWorld-0.0.3.dist-info/top_level.txt
cheaquiHelloWorld-0.0.3.dist-info/RECORD
