Metadata-Version: 2.1
Name: cheaquiHelloWorld
Version: 0.0.3
Summary: Say hello!
Classifier: Programming Language :: Python :: 3
Classifier: Programming Language :: Python :: 3.6
Classifier: License :: OSI Approved :: GNU General Public License v2 or later (GPLv2+)
Classifier: Operating System :: OS Independent
License-File: LICENSE
Requires-Dist: blessings (~=1.7)
